orange3_db_connections-0.2.3.dist-info/licenses/LICENSE
orangecontrib/__init__.py
orangecontrib/dbconnections/__init__.py
orangecontrib/dbconnections/utils/__init__.py
orangecontrib/dbconnections/utils/driver_installer.py
orangecontrib/dbconnections/widgets/__init__.py
orangecontrib/dbconnections/widgets/_base_connection.py
orangecontrib/dbconnections/widgets/ow_clickhouse_connection.py
orangecontrib/dbconnections/widgets/ow_env_check.py
orangecontrib/dbconnections/widgets/ow_mssql_connection.py
orangecontrib/dbconnections/widgets/ow_mysql_connection.py
orangecontrib/dbconnections/widgets/ow_oracle_connection.py
orangecontrib/dbconnections/widgets/ow_pg_connection.py
orangecontrib/dbconnections/widgets/icons/addon_icon.png
orangecontrib/dbconnections/widgets/icons/clickhouse.png
orangecontrib/dbconnections/widgets/icons/mariadb.png
orangecontrib/dbconnections/widgets/icons/msql.png
orangecontrib/dbconnections/widgets/icons/mysql.png
orangecontrib/dbconnections/widgets/icons/oracle.png
orangecontrib/dbconnections/widgets/icons/postgres.png
orangecontrib/dbconnections/widgets/icons/sqlite.png
orange3_db_connections-0.2.3.dist-info/METADATA
orange3_db_connections-0.2.3.dist-info/WHEEL
orange3_db_connections-0.2.3.dist-info/entry_points.txt
orange3_db_connections-0.2.3.dist-info/top_level.txt
orange3_db_connections-0.2.3.dist-info/RECORD
