Metadata-Version: 2.4
Name: orange3-db-connections
Version: 0.2.3
Summary: DB Connections – Add-on Orange untuk membuat koneksi database (PostgreSQL, MySQL, SQL Server, SQLite, ClickHouse).
Author-email: Devi Ardiana <deviardn@gmail.com>
License: MIT
Project-URL: Homepage, https://github.com/deviardn/orange3-db-connections
Classifier: Programming Language :: Python :: 3
Classifier: License :: OSI Approved :: MIT License
Classifier: Operating System :: OS Independent
Requires-Python: >=3.9
License-File: LICENSE
Requires-Dist: orange3>=3.36.0
Requires-Dist: sqlalchemy>=2.0
Requires-Dist: AnyQt>=0.0.13
Requires-Dist: PyQt5>=5.15
Requires-Dist: PyQtWebEngine>=5.15
Provides-Extra: postgresql
Requires-Dist: psycopg2-binary>=2.9; extra == "postgresql"
Provides-Extra: mysql
Requires-Dist: pymysql>=1.0; extra == "mysql"
Provides-Extra: mssql
Requires-Dist: pyodbc>=4.0; extra == "mssql"
Provides-Extra: clickhouse
Requires-Dist: clickhouse-connect>=0.7; extra == "clickhouse"
Provides-Extra: oracle
Requires-Dist: cx-Oracle>=8.3; extra == "oracle"
Dynamic: license-file
